youtube_discussion_tree_api/__init__.py
youtube_discussion_tree_api/_api.py
youtube_discussion_tree_api/_conflicts.py
youtube_discussion_tree_api/_errors.py
youtube_discussion_tree_api/_http.py
youtube_discussion_tree_api/_quota.py
youtube_discussion_tree_api/_tree.py
youtube_discussion_tree_api/_viz.py
youtube_discussion_tree_api/_xml.py
youtube_discussion_tree_api/tests/__init__.py
youtube_discussion_tree_api/tests/test_api.py
youtube_discussion_tree_api/tests/test_conflicts.py
youtube_discussion_tree_api/tests/test_http.py
youtube_discussion_tree_api/tests/test_quota.py
youtube_discussion_tree_api/tests/test_tree.py
youtube_discussion_tree_api/tests/test_xml.py
youtube_discussion_tree_api/utils/__init__.py
youtube_discussion_tree_api/utils/node.py
youtube_discussion_tree_api/utils/quota.py
youtube_discussion_tree_api/utils/video.py
youtube_discussion_tree_api-1.0.3.dist-info/LICENSE
youtube_discussion_tree_api-1.0.3.dist-info/METADATA
youtube_discussion_tree_api-1.0.3.dist-info/WHEEL
youtube_discussion_tree_api-1.0.3.dist-info/top_level.txt
youtube_discussion_tree_api-1.0.3.dist-info/RECORD
