Metadata-Version: 2.1
Name: youtube-discussion-tree-api
Version: 1.0.3
Summary: This is a python API that allows you to obtain the discussion that occurs in the comments of a YouTube video as a tree structure.
Home-page: https://github.com/quimpm/youtube_discussion_tree
Author: Quim10^-12
Author-email: quimpm99@gmail.com
License: MIT
Platform: UNKNOWN
Classifier: Programming Language :: Python :: 3.8
Classifier: License :: OSI Approved :: MIT License
Classifier: Operating System :: OS Independent
Requires-Dist: nltk
Requires-Dist: requests
Requires-Dist: torch
Requires-Dist: torchaudio
Requires-Dist: torchvision
Requires-Dist: transformers
Requires-Dist: treelib
Requires-Dist: youtube-transcript-api
